[{"disccalcon":"Invoice total","due":{"daysforward":30},"penalty":{"percentamount":1,"penaltycycle":"Weekly"},"name":"2/10 Net30","description":"2/10 Net30","discount":{"amount":2,"daysforward":10,"gracedays":1},"status":"active"},{"disccalcon":"Invoice total","due":{"daysforward":30},"penalty":{"percentamount":1,"penaltycycle":"No Penalty","gracedays":5},"name":"Net 30","description":"Net 30","status":"active"},{"disccalcon":"Invoice total","due":{"daysforward":15},"penalty":{"percentamount":1,"penaltycycle":"Weekly","gracedays":5},"name":"Net15","description":"2/10 Net30","status":"active"},{"disccalcon":"Invoice total","due":{"daysforward":3},"penalty":{"amount":1,"penaltycycle":"Weekly","gracedays":30},"name":"Upon Receipt","description":"Upon Receipt","status":"active"}]